iterprinter/__init__.py
iterprinter/iterprinter.py
iterprinter-0.1.1.dist-info/METADATA
iterprinter-0.1.1.dist-info/WHEEL
iterprinter-0.1.1.dist-info/top_level.txt
iterprinter-0.1.1.dist-info/RECORD
