Metadata-Version: 2.1
Name: iterprinter
Version: 0.1.1
Summary: An iteration history printer
Home-page: UNKNOWN
Author: Jeffrey M. Hokanson
License: UNKNOWN
Platform: UNKNOWN
